[
  {
    "id": 1,
    "title": "2nd  Post",
    "content": "Test",
    "username": "helloworld",
    "icon": "",
    "emoji": [
      {
        "emojiUsed": true,
        "emojiOne": 1
      },
      {
        "emojiUsed": false,
        "emojiTwo": 0
      },
      {
        "emojiUsed": false,
        "emojiThree": 0
      }
    ],
    "gif": [],
    "date": "02/10/90",
    "time": "12:24",
    "comments": [
      {
        "commentUsername": "idk123",
        "commentIcons": "sdf.png",
        "commentBody": "Testing",
        "commentDate": "03/05/20"
      }
    ]
  },
  {
    "id": 2,
    "title": "fds",
    "content": "dfs",
    "username": "enlightened-reindeer270",
    "icon": "https://xsgames.co/randomusers/assets/avatars/pixel/0.jpg",
    "emoji": [
      {
        "emojiUsed": false,
        "emojiOne": 0
      },
      {
        "emojiUsed": false,
        "emojiTwo": 0
      },
      {
        "emojiUsed": false,
        "emojiThree": 0
      }
    ],
    "gif": [],
    "date": "04/10/2022",
    "time": "11:00:36",
    "comments": [
      {}
    ]
  }
]